ALUunit/ALU.v
// ALU unit

module alu (data1,data2,opcode,Output);
    input [31:0] data1,data2;
    input [4:0] opcode;

    output reg [31:0] Output;

    wire [31:0] MULH_result,MULHU_result,MULHSU_result;
    wire [63:0] mulh_result,mulhu_result,mulhsu_result;
    wire [31:0] SLT_result;

    assign mulh_result = $signed (data1)*$signed(data2) ;
    assign MULH_result = mulh_result[63:31];

    assign mulhu_result = $signed (data1)*$unsigned(data2) ;
    assign MULHU_result = mulhu_result[63:31];

    assign mulhsu_result = $unsigned (data1)*$unsigned(data2) ;
    assign MULHSU_result = mulhsu_result[63:31];

    assign SLT_result = (data1<data2)?32'b1:32'b0;
    
    always @(*) begin
        case (opcode)
            5'b00000:Output = data1+data2;      //ADD
            5'b00001:Output = data1-data2;      //SUB
            5'b00010:Output = data1|data2;      //OR
            5'b00011:Output = data1^data2;      //XOR
            5'b00100:Output = data1&data2;      //AND
            5'b00101:Output = data1>>data2;      //SLR
            5'b00110:Output = data1<<data2;      //SLL
            5'b00111:Output = data1>>>data2;      //SRA
            5'b01000:Output = data1*data2;      //MUL
            5'b01001:Output = MULH_result;    //MULH
            5'b01010:Output = MULHU_result;    //MULHU
            5'b01011:Output = MULHSU_result;    //MULHSU
            5'b01100:Output = $signed(data1)/$signed(data2);//DIV
            5'b01101:Output = $unsigned(data1)/$unsigned(data2);//DIVH
            5'b01110:Output = $signed(data1)% $signed(data2);//REM
            5'b01111:Output = $unsigned(data1)% $unsigned(data2);//REMU
            5'b10000:Output = SLT_result; //SLT
            5'b10001:Output = data2;
            default:Output = 32'b0;
        endcase
    end
   
endmodule

ALUunit/ALUtestbench.v
//ALU testbench
`timescale 1ps/1ps

module tb_ALU ;
    reg[31:0]DATA1,DATA2;
    reg[4:0]OPCODE;
    wire[31:0]ALU_OUTPUT;

    integer i;

    alu test_unit(DATA1,DATA2,OPCODE,ALU_OUTPUT);                       // initiating the alu module 
    initial begin
        $monitor("Time=%0t, Data1=%d, Data2=%d, Output=%d", $time, DATA1, DATA2,ALU_OUTPUT);

            
        DATA1 = 32'd6;
        DATA2 = 32'd3;
        OPCODE = 5'd0;
            

        for (i=0;i<=17;i++)
        begin
            OPCODE =i;
            #5;
        end
        $finish;
    end
    
endmodule

ALUunit/waveform.vcd
$date
	Fri Dec 06 12:59:24 2024
$end
$version
	Icarus Verilog
$end
$timescale
	1ps
$end
$scope module tb_ALU $end
$var wire 32 ! ALU_OUTPUT [31:0] $end
$var reg 32 " DATA1 [31:0] $end
$var reg 32 # DATA2 [31:0] $end
$var reg 5 $ OPCODE [4:0] $end
$var integer 32 % i [31:0] $end
$scope module test_unit $end
$var wire 32 & data1 [31:0] $end
$var wire 32 ' data2 [31:0] $end
$var wire 5 ( opcode [4:0] $end
$var wire 64 ) mulhu_result [63:0] $end
$var wire 64 * mulhsu_result [63:0] $end
$var wire 64 + mulh_result [63:0] $end
$var wire 32 , SLT_result [31:0] $end
$var wire 32 - MULH_result [31:0] $end
$var wire 32 . MULHU_result [31:0] $end
$var wire 32 / MULHSU_result [31:0] $end
$var reg 32 0 Output [31:0] $end
$upscope $end
$upscope $end
$enddefinitions $end
$comment Show the parameter values. $end
$dumpall
$end
#0
$dumpvars
b1001 0
b0 /
b0 .
b0 -
b0 ,
b10010 +
b10010 *
b10010 )
b0 (
b11 '
b110 &
b0 %
b0 $
b11 #
b110 "
b1001 !
$end
#5
b11 !
b11 0
b1 $
b1 (
b1 %
#10
b111 !
b111 0
b10 $
b10 (
b10 %
#15
b101 !
b101 0
b11 $
b11 (
b11 %
#20
b10 !
b10 0
b100 $
b100 (
b100 %
#25
b0 !
b0 0
b101 $
b101 (
b101 %
#30
b110000 !
b110000 0
b110 $
b110 (
b110 %
#35
b0 !
b0 0
b111 $
b111 (
b111 %
#40
b10010 !
b10010 0
b1000 $
b1000 (
b1000 %
#45
b0 !
b0 0
b1001 $
b1001 (
b1001 %
#50
b1010 $
b1010 (
b1010 %
#55
b1011 $
b1011 (
b1011 %
#60
b10 !
b10 0
b1100 $
b1100 (
b1100 %
#65
b1101 $
b1101 (
b1101 %
#70
b0 !
b0 0
b1110 $
b1110 (
b1110 %
#75
b1111 $
b1111 (
b1111 %
#80
b10000 $
b10000 (
b10000 %
#85
b11 !
b11 0
b10001 $
b10001 (
b10001 %
#90
b10010 %
