RegisterFile/registerfile.v

module RegisterFile (RS1,RS2,WRITEDATA,WRITEADDRESS,WRITEENABLE,RESET,CLK,DATA1,DATA2);
    input [4:0] RS1,RS2,WRITEADDRESS;
    input [31:0] WRITEDATA;
    input CLK,WRITEENABLE,RESET;
    output reg [31:0] DATA1,DATA2;
    reg [31:0] registers [0:31];

    integer i;
    always @(posedge CLK)
    begin
        if(RESET)
        begin
            #1
            for (i = 0;i<32 ;i++ )
            begin
            registers[i] <= 0;
            end 
        end
        else if(WRITEENABLE && WRITEADDRESS != 5'd0)
        begin
            #1
            registers[WRITEADDRESS] <= WRITEDATA;
        end 
    end
    always @(RS1,RS2)
    begin
        #2
        DATA1 <= registers[RS1];
        DATA2 <= registers[RS2];
    end

endmodule

module RegisterFile_tb;
    reg [4:0] RS1, RS2, WRITEADDRESS;
    reg [31:0] WRITEDATA;
    reg CLK, WRITEENABLE, RESET;
    wire [31:0] DATA1, DATA2;

    // Instantiate the RegisterFile module
    RegisterFile uut (
        .RS1(RS1), .RS2(RS2), .WRITEADDRESS(WRITEADDRESS),
        .WRITEDATA(WRITEDATA), .CLK(CLK), .WRITEENABLE(WRITEENABLE),
        .RESET(RESET), .DATA1(DATA1), .DATA2(DATA2)
    );

    // Clock generation
    initial CLK = 0;
    always #5 CLK = ~CLK;

    initial begin

        $dumpfile("wave.vcd");
        $dumpvars(0,RegisterFile_tb);

        // Test case: Reset
        RESET = 1;
        WRITEENABLE = 0;
        #10 RESET = 0;

        // Test case: Write to register 1
        WRITEADDRESS = 5'd1;
        WRITEDATA = 32'hA5A5A5A5;
        WRITEENABLE = 1;
        #10 WRITEENABLE = 0;

        // Test case: Read from register 1
        RS1 = 5'd1;
        RS2 = 5'd0; // Register 0 should remain 0
        #10;

        // Test case: Write to register 2
        WRITEADDRESS = 5'd2;
        WRITEDATA = 32'h5A5A5A5A;
        WRITEENABLE = 1;
        #10 WRITEENABLE = 0;

        // Test case: Read from registers 1 and 2
        RS1 = 5'd1;
        RS2 = 5'd2;
        #10;

        $finish;
    end
endmodule

RegisterFile/wave.vcd
$date
	Wed Dec 04 14:11:00 2024
$end
$version
	Icarus Verilog
$end
$timescale
	1s
$end
$scope module RegisterFile_tb $end
$var wire 32 ! DATA2 [31:0] $end
$var wire 32 " DATA1 [31:0] $end
$var reg 1 # CLK $end
$var reg 1 $ RESET $end
$var reg 5 % RS1 [4:0] $end
$var reg 5 & RS2 [4:0] $end
$var reg 5 ' WRITEADDRESS [4:0] $end
$var reg 32 ( WRITEDATA [31:0] $end
$var reg 1 ) WRITEENABLE $end
$scope module uut $end
$var wire 1 # CLK $end
$var wire 1 $ RESET $end
$var wire 5 * RS1 [4:0] $end
$var wire 5 + RS2 [4:0] $end
$var wire 5 , WRITEADDRESS [4:0] $end
$var wire 32 - WRITEDATA [31:0] $end
$var wire 1 ) WRITEENABLE $end
$var reg 32 . DATA1 [31:0] $end
$var reg 32 / DATA2 [31:0] $end
$var integer 32 0 i [31:0] $end
$upscope $end
$upscope $end
$enddefinitions $end
$comment Show the parameter values. $end
$dumpall
$end
#0
$dumpvars
bx 0
bx /
bx .
bx -
bx ,
bx +
bx *
0)
bx (
bx '
bx &
bx %
1$
0#
bx "
bx !
$end
#5
1#
#6
b100000 0
#10
0#
1)
b10100101101001011010010110100101 (
b10100101101001011010010110100101 -
b1 '
b1 ,
0$
#15
1#
#20
0#
b0 &
b0 +
b1 %
b1 *
0)
#22
b0 !
b0 /
b10100101101001011010010110100101 "
b10100101101001011010010110100101 .
#25
1#
#30
0#
1)
b1011010010110100101101001011010 (
b1011010010110100101101001011010 -
b10 '
b10 ,
#35
1#
#40
0#
b10 &
b10 +
0)
#42
b1011010010110100101101001011010 !
b1011010010110100101101001011010 /
