ID_IF_pipeLIne/ID_IF_register.v
module ID_IF_register(CLK,INSTRUCTION,PC,PC_PLUS_4,RESET,INSTRUCTION_OUT,PC_OUT,PC_PLUS_4_OUT);
input RESET,CLK;
input[31:0] INSTRUCTION,PC,PC_PLUS_4;
output reg [31:0] INSTRUCTION_OUT,PC_OUT,PC_PLUS_4_OUT;


always @(posedge CLK) begin
    if (RESET==1) begin
        INSTRUCTION_OUT <= 0;
        PC_OUT <= 0;
        PC_PLUS_4_OUT <= 0;
    end
    else begin
    INSTRUCTION_OUT <= INSTRUCTION;
    PC_OUT <= PC;
    PC_PLUS_4_OUT <= PC_PLUS_4;
    end
   
end

endmodule

ID_IF_pipeLIne/IF_ID_register_tb.v


module TB_ID_IF_register;
    // Inputs
    reg CLK;
    reg RESET;
    reg [31:0] INSTRUCTION;
    reg [31:0] PC;
    reg [31:0] PC_PLUS_4;

    // Outputs
    wire [31:0] INSTRUCTION_OUT;
    wire [31:0] PC_OUT;
    wire [31:0] PC_PLUS_4_OUT;

    // Instantiate the module
    ID_IF_register uut (
        .CLK(CLK),
        .RESET(RESET),
        .INSTRUCTION(INSTRUCTION),
        .PC(PC),
        .PC_PLUS_4(PC_PLUS_4),
        .INSTRUCTION_OUT(INSTRUCTION_OUT),
        .PC_OUT(PC_OUT),
        .PC_PLUS_4_OUT(PC_PLUS_4_OUT)
    );

    // Clock generation
    initial begin
        CLK = 0;
        forever #5 CLK = ~CLK;  // 10 ns clock period
    end

    // Test sequence
    initial begin
        // Initialize inputs
        RESET = 1;
        INSTRUCTION = 0;
        PC = 0;
        PC_PLUS_4 = 0;

        // Apply reset
        #10;
        RESET = 0;

        // Apply first set of inputs
        #10;
        INSTRUCTION = 32'hAABBCCDD;
        PC = 32'h00000010;
        PC_PLUS_4 = 32'h00000014;

        // Wait for the register to update
        #20;

        // Apply second set of inputs
        INSTRUCTION = 32'h12345678;
        PC = 32'h00000020;
        PC_PLUS_4 = 32'h00000024;

        // Wait for the register to update
        #20;

        // Apply reset again
        RESET = 1;
        #10;
        RESET = 0;

        // Final inputs
        INSTRUCTION = 32'hFFFFFFFF;
        PC = 32'h00000030;
        PC_PLUS_4 = 32'h00000034;

        // Wait and finish
        #20;
        $finish;
    end

    // Monitor outputs
    initial begin
        $dumpfile("if_id_pipeline.vcd");
        $dumpvars(0, TB_ID_IF_register);
        $monitor("Time: %0d | RESET: %b | CLK: %b | INSTRUCTION: %h | PC: %h | PC_PLUS_4: %h | INSTRUCTION_OUT: %h | PC_OUT: %h | PC_PLUS_4_OUT: %h",
                 $time, RESET, CLK, INSTRUCTION, PC, PC_PLUS_4, INSTRUCTION_OUT, PC_OUT, PC_PLUS_4_OUT);
    end
endmodule

ID_IF_pipeLIne/if_id_pipeline.vcd
$date
	Wed Jan 15 21:11:54 2025
$end
$version
	Icarus Verilog
$end
$timescale
	1s
$end
$scope module TB_ID_IF_register $end
$var wire 32 ! PC_PLUS_4_OUT [31:0] $end
$var wire 32 " PC_OUT [31:0] $end
$var wire 32 # INSTRUCTION_OUT [31:0] $end
$var reg 1 $ CLK $end
$var reg 32 % INSTRUCTION [31:0] $end
$var reg 32 & PC [31:0] $end
$var reg 32 ' PC_PLUS_4 [31:0] $end
$var reg 1 ( RESET $end
$scope module uut $end
$var wire 1 $ CLK $end
$var wire 32 ) INSTRUCTION [31:0] $end
$var wire 32 * PC [31:0] $end
$var wire 32 + PC_PLUS_4 [31:0] $end
$var wire 1 ( RESET $end
$var reg 32 , INSTRUCTION_OUT [31:0] $end
$var reg 32 - PC_OUT [31:0] $end
$var reg 32 . PC_PLUS_4_OUT [31:0] $end
$upscope $end
$upscope $end
$enddefinitions $end
$comment Show the parameter values. $end
$dumpall
$end
#0
$dumpvars
bx .
bx -
bx ,
b0 +
b0 *
b0 )
1(
b0 '
b0 &
b0 %
0$
bx #
bx "
bx !
$end
#5
1$
#6
b0 !
b0 .
b0 "
b0 -
b0 #
b0 ,
#10
0$
0(
#15
1$
#20
0$
b10100 '
b10100 +
b10000 &
b10000 *
b10101010101110111100110011011101 %
b10101010101110111100110011011101 )
#25
1$
#27
b10100 !
b10100 .
b10000 "
b10000 -
b10101010101110111100110011011101 #
b10101010101110111100110011011101 ,
#30
0$
#35
1$
#40
0$
b100100 '
b100100 +
b100000 &
b100000 *
b10010001101000101011001111000 %
b10010001101000101011001111000 )
#45
1$
#47
b100100 !
b100100 .
b100000 "
b100000 -
b10010001101000101011001111000 #
b10010001101000101011001111000 ,
#50
0$
#55
1$
#60
0$
1(
#65
1$
#66
b0 !
b0 .
b0 "
b0 -
b0 #
b0 ,
#70
0$
b110100 '
b110100 +
b110000 &
b110000 *
b11111111111111111111111111111111 %
b11111111111111111111111111111111 )
0(
#75
1$
#77
b110100 !
b110100 .
b110000 "
b110000 -
b11111111111111111111111111111111 #
b11111111111111111111111111111111 ,
