EX_MEM_pipeline/EX_MEM_pipeline.v
module EX_MEM_pipeline (CLK,RESET,WRITE_ENABLE,MEM_ACCESS,MEM_WRITE,MEM_READ,ALU_OUTPUT,WRITE_ADDRESS,FUNCT3,DATA2,WRITE_ENABLE_OUT,MEM_ACCESS_OUT,MEM_WRITE_OUT,MEM_READ_OUT,ALU_OUTPUT_OUT,WRITE_ADDRESS_OUT,FUNCT3_OUT,DATA2_OUT);
    input CLK,RESET;
    input WRITE_ENABLE,MEM_ACCESS,MEM_WRITE,MEM_READ;
    input[31:0] ALU_OUTPUT,DATA2;
    input[4:0] WRITE_ADDRESS;
    input[2:0] FUNCT3;
    output reg WRITE_ENABLE_OUT,MEM_ACCESS_OUT,MEM_WRITE_OUT,MEM_READ_OUT;
    output reg[31:0] ALU_OUTPUT_OUT,DATA2_OUT;
    output reg[4:0] WRITE_ADDRESS_OUT;
    output reg[2:0] FUNCT3_OUT;

    always @(posedge CLK) begin
        if(RESET) begin
            #1
            WRITE_ENABLE_OUT <= 1'bx;
            MEM_ACCESS_OUT <= 1'bx;
            MEM_WRITE_OUT <= 1'bx;
            MEM_READ_OUT <= 1'bx;
            ALU_OUTPUT_OUT <= 32'bx;
            WRITE_ADDRESS_OUT <= 5'bx;
            FUNCT3_OUT <= 3'bx;
            DATA2_OUT <= 32'bx;
        end
        else begin
            #2
            WRITE_ENABLE_OUT <= WRITE_ENABLE;
            MEM_ACCESS_OUT <= MEM_ACCESS;
            MEM_WRITE_OUT <= MEM_WRITE;
            MEM_READ_OUT <= MEM_READ;
            ALU_OUTPUT_OUT <= ALU_OUTPUT;
            WRITE_ADDRESS_OUT <= WRITE_ADDRESS;
            FUNCT3_OUT <= FUNCT3;
            DATA2_OUT <= DATA2;
        end
    end
    
endmodule

EX_MEM_pipeline/EX_MEM_pipeline_tb.v
module EX_MEM_pipeline_tb;

    // Inputs
    reg CLK;
    reg RESET;
    reg WRITE_ENABLE;
    reg MEM_ACCESS;
    reg MEM_WRITE;
    reg MEM_READ;
    reg [31:0] ALU_OUTPUT;
    reg [31:0] DATA2;
    reg [4:0] WRITE_ADDRESS;
    reg [2:0] FUNCT3;

    // Outputs
    wire WRITE_ENABLE_OUT;
    wire MEM_ACCESS_OUT;
    wire MEM_WRITE_OUT;
    wire MEM_READ_OUT;
    wire [31:0] ALU_OUTPUT_OUT;
    wire [31:0] DATA2_OUT;
    wire [4:0] WRITE_ADDRESS_OUT;
    wire [2:0] FUNCT3_OUT;

    // Instantiate the Unit Under Test (UUT)
    EX_MEM_pipeline uut (
        .CLK(CLK),
        .RESET(RESET),
        .WRITE_ENABLE(WRITE_ENABLE),
        .MEM_ACCESS(MEM_ACCESS),
        .MEM_WRITE(MEM_WRITE),
        .MEM_READ(MEM_READ),
        .ALU_OUTPUT(ALU_OUTPUT),
        .DATA2(DATA2),
        .WRITE_ADDRESS(WRITE_ADDRESS),
        .FUNCT3(FUNCT3),
        .WRITE_ENABLE_OUT(WRITE_ENABLE_OUT),
        .MEM_ACCESS_OUT(MEM_ACCESS_OUT),
        .MEM_WRITE_OUT(MEM_WRITE_OUT),
        .MEM_READ_OUT(MEM_READ_OUT),
        .ALU_OUTPUT_OUT(ALU_OUTPUT_OUT),
        .DATA2_OUT(DATA2_OUT),
        .WRITE_ADDRESS_OUT(WRITE_ADDRESS_OUT),
        .FUNCT3_OUT(FUNCT3_OUT)
    );

    // Clock generation
    always #5 CLK = ~CLK; // 10 time unit clock period

    initial begin
        // Initialize inputs
        CLK = 0;
        RESET = 1;
        WRITE_ENABLE = 0;
        MEM_ACCESS = 0;
        MEM_WRITE = 0;
        MEM_READ = 0;
        ALU_OUTPUT = 32'b0;
        DATA2 = 32'b0;
        WRITE_ADDRESS = 5'b0;
        FUNCT3 = 3'b0;

        // Apply reset
        #10 RESET = 0;

        // Apply test stimulus
        #10 WRITE_ENABLE = 1;
            MEM_ACCESS = 1;
            MEM_WRITE = 1;
            MEM_READ = 0;
            ALU_OUTPUT = 32'hA5A5A5A5;
            DATA2 = 32'h5A5A5A5A;
            WRITE_ADDRESS = 5'b10101;
            FUNCT3 = 3'b111;

        #10 WRITE_ENABLE = 0;
            MEM_ACCESS = 0;
            MEM_WRITE = 0;
            MEM_READ = 1;
            ALU_OUTPUT = 32'hFFFFFFFF;
            DATA2 = 32'h00000000;
            WRITE_ADDRESS = 5'b00001;
            FUNCT3 = 3'b000;

        // Deassert reset during operation
        #10 RESET = 1; // Reset active
        #10 RESET = 0; // Reset deactivated

        // Test final state
        #10 WRITE_ENABLE = 1;
            MEM_ACCESS = 1;
            MEM_WRITE = 0;
            MEM_READ = 1;
            ALU_OUTPUT = 32'h12345678;
            DATA2 = 32'h87654321;
            WRITE_ADDRESS = 5'b11111;
            FUNCT3 = 3'b101;

        // End simulation
        #20 $finish;
    end

    initial begin
        // Dump waves for GTKWave
        $dumpfile("EX_MEM_pipeline_tb.vcd");
        $dumpvars(0, EX_MEM_pipeline_tb);

        // Monitor signal changes
        $monitor("Time = %0t | RESET = %b | WRITE_ENABLE = %b | MEM_ACCESS = %b | MEM_WRITE = %b | MEM_READ = %b | ALU_OUTPUT = %h | DATA2 = %h | WRITE_ADDRESS = %b | FUNCT3 = %b | WRITE_ENABLE_OUT = %b | MEM_ACCESS_OUT = %b | MEM_WRITE_OUT = %b | MEM_READ_OUT = %b | ALU_OUTPUT_OUT = %h | DATA2_OUT = %h | WRITE_ADDRESS_OUT = %b | FUNCT3_OUT = %b",
                 $time, RESET, WRITE_ENABLE, MEM_ACCESS, MEM_WRITE, MEM_READ, ALU_OUTPUT, DATA2, WRITE_ADDRESS, FUNCT3,
                 WRITE_ENABLE_OUT, MEM_ACCESS_OUT, MEM_WRITE_OUT, MEM_READ_OUT, ALU_OUTPUT_OUT, DATA2_OUT, WRITE_ADDRESS_OUT, FUNCT3_OUT);
    end

endmodule

EX_MEM_pipeline/EX_MEM_pipeline_tb.vcd
$date
	Mon Dec 30 13:37:29 2024
$end
$version
	Icarus Verilog
$end
$timescale
	1s
$end
$scope module EX_MEM_pipeline_tb $end
$var wire 1 ! WRITE_ENABLE_OUT $end
$var wire 5 " WRITE_ADDRESS_OUT [4:0] $end
$var wire 1 # MEM_WRITE_OUT $end
$var wire 1 $ MEM_READ_OUT $end
$var wire 1 % MEM_ACCESS_OUT $end
$var wire 3 & FUNCT3_OUT [2:0] $end
$var wire 32 ' DATA2_OUT [31:0] $end
$var wire 32 ( ALU_OUTPUT_OUT [31:0] $end
$var reg 32 ) ALU_OUTPUT [31:0] $end
$var reg 1 * CLK $end
$var reg 32 + DATA2 [31:0] $end
$var reg 3 , FUNCT3 [2:0] $end
$var reg 1 - MEM_ACCESS $end
$var reg 1 . MEM_READ $end
$var reg 1 / MEM_WRITE $end
$var reg 1 0 RESET $end
$var reg 5 1 WRITE_ADDRESS [4:0] $end
$var reg 1 2 WRITE_ENABLE $end
$scope module uut $end
$var wire 32 3 ALU_OUTPUT [31:0] $end
$var wire 1 * CLK $end
$var wire 32 4 DATA2 [31:0] $end
$var wire 3 5 FUNCT3 [2:0] $end
$var wire 1 - MEM_ACCESS $end
$var wire 1 . MEM_READ $end
$var wire 1 / MEM_WRITE $end
$var wire 1 0 RESET $end
$var wire 5 6 WRITE_ADDRESS [4:0] $end
$var wire 1 2 WRITE_ENABLE $end
$var reg 32 7 ALU_OUTPUT_OUT [31:0] $end
$var reg 32 8 DATA2_OUT [31:0] $end
$var reg 3 9 FUNCT3_OUT [2:0] $end
$var reg 1 % MEM_ACCESS_OUT $end
$var reg 1 $ MEM_READ_OUT $end
$var reg 1 # MEM_WRITE_OUT $end
$var reg 5 : WRITE_ADDRESS_OUT [4:0] $end
$var reg 1 ! WRITE_ENABLE_OUT $end
$upscope $end
$upscope $end
$enddefinitions $end
$comment Show the parameter values. $end
$dumpall
$end
#0
$dumpvars
bx :
bx 9
bx 8
bx 7
b0 6
b0 5
b0 4
b0 3
02
b0 1
10
0/
0.
0-
b0 ,
b0 +
0*
b0 )
bx (
bx '
bx &
x%
x$
x#
bx "
x!
$end
#5
1*
#10
0*
00
#15
b0 '
b0 8
b0 &
b0 9
b0 "
b0 :
b0 (
b0 7
0$
0#
0%
0!
1*
#20
0*
b111 ,
b111 5
b10101 1
b10101 6
b1011010010110100101101001011010 +
b1011010010110100101101001011010 4
b10100101101001011010010110100101 )
b10100101101001011010010110100101 3
1/
1-
12
#25
b1011010010110100101101001011010 '
b1011010010110100101101001011010 8
b111 &
b111 9
b10101 "
b10101 :
b10100101101001011010010110100101 (
b10100101101001011010010110100101 7
1#
1%
1!
1*
#30
0*
b0 ,
b0 5
b1 1
b1 6
b0 +
b0 4
b11111111111111111111111111111111 )
b11111111111111111111111111111111 3
1.
0/
0-
02
#35
b0 '
b0 8
b0 &
b0 9
b1 "
b1 :
b11111111111111111111111111111111 (
b11111111111111111111111111111111 7
1$
0#
0%
0!
1*
#40
0*
10
#45
bx '
bx 8
bx &
bx 9
bx "
bx :
bx (
bx 7
x$
x#
x%
x!
1*
#50
0*
00
#55
b0 '
b0 8
b0 &
b0 9
b1 "
b1 :
b11111111111111111111111111111111 (
b11111111111111111111111111111111 7
1$
0#
0%
0!
1*
#60
0*
b101 ,
b101 5
b11111 1
b11111 6
b10000111011001010100001100100001 +
b10000111011001010100001100100001 4
b10010001101000101011001111000 )
b10010001101000101011001111000 3
1-
12
#65
b10000111011001010100001100100001 '
b10000111011001010100001100100001 8
b101 &
b101 9
b11111 "
b11111 :
b10010001101000101011001111000 (
b10010001101000101011001111000 7
1%
1!
1*
